skpy/__init__.py
skpy/chat.py
skpy/conn.py
skpy/core.py
skpy/event.py
skpy/main.py
skpy/msg.py
skpy/user.py
skpy/util.py
SkPy-0.10.7.dist-info/LICENSE.txt
SkPy-0.10.7.dist-info/METADATA
SkPy-0.10.7.dist-info/WHEEL
SkPy-0.10.7.dist-info/top_level.txt
SkPy-0.10.7.dist-info/RECORD
