Metadata-Version: 2.1
Name: SkPy
Version: 0.10.7
Summary: An unofficial Python library for interacting with the Skype HTTP API.
Home-page: https://skpy.t.allofti.me
Download-URL: https://github.com/Terrance/SkPy/releases
Author: Ollie Terrance
Classifier: Development Status :: 4 - Beta
Classifier: Intended Audience :: Developers
Classifier: Topic :: Communications :: Chat
Classifier: Topic :: Software Development :: Libraries
License-File: LICENSE.txt
Requires-Dist: beautifulsoup4
Requires-Dist: requests
